ipyantd/__init__.py
ipyantd/_version.py
ipyantd/core.py
ipyantd/mixins.py
ipyantd/static/extension.js
ipyantd/static/index.js
ipyantd/static/index.js.map
ipyantd-0.1.11.data/data/etc/jupyter/nbconfig/notebook.d/ipyantd.json
ipyantd-0.1.11.data/data/share/jupyter/nbextensions/ipyantd/extension.js
ipyantd-0.1.11.data/data/share/jupyter/nbextensions/ipyantd/index.js
ipyantd-0.1.11.data/data/share/jupyter/nbextensions/ipyantd/index.js.map
ipyantd-0.1.11.dist-info/METADATA
ipyantd-0.1.11.dist-info/RECORD
ipyantd-0.1.11.dist-info/WHEEL
ipyantd-0.1.11.dist-info/top_level.txt
